osc_sdk/__init__.py
osc_sdk/osc-cli-completion.bash
osc_sdk/sdk.py
osc_sdk/test_auth.py
osc_sdk/test_errors.py
osc_sdk/test_noauth.py
osc_sdk-1.11.0.dist-info/LICENSE
osc_sdk-1.11.0.dist-info/METADATA
osc_sdk-1.11.0.dist-info/WHEEL
osc_sdk-1.11.0.dist-info/entry_points.txt
osc_sdk-1.11.0.dist-info/top_level.txt
osc_sdk-1.11.0.dist-info/RECORD
