Metadata-Version: 2.1
Name: osc-sdk
Version: 1.11.0
Summary: Outscale API SDK and CLI
Home-page: https://github.com/outscale/osc-cli
Author: Outscale SAS
Author-email: contact@outscale.com
License: BSD
Classifier: License :: OSI Approved :: BSD License
Classifier: Programming Language :: Python :: 3
Classifier: Programming Language :: Python :: 3.6
Classifier: Programming Language :: Python :: 3.7
Classifier: Programming Language :: Python :: 3.8
Classifier: Programming Language :: Python :: 3.9
Classifier: Programming Language :: Python :: 3.10
Classifier: Operating System :: OS Independent
License-File: LICENSE
